{"type":"footer","name":"t:sections.footer-group.name","sections":{"footer-promotions":{"type":"footer-promotions","settings":{"hide_homepage":false}},"footer":{"type":"footer","blocks":{"9e680033-3ce9-4c32-8ec1-a994ad408f27":{"type":"logo_social","settings":{"logo":"shopify:\/\/shop_images\/logo_13ad89c9-7387-4f3f-92e0-a79b250156be.png","desktop_logo_height":120,"container_width":25}},"f79f7187-a92b-4f1f-9d47-6305d2baca5f":{"type":"custom","settings":{"show_footer_title":true,"title":"Contact Us","text":"<p>Detroit, Michigan USA<\/p><p>+1-313-355-3058<\/p><p>info@printarun.com<\/p>","container_width":25}},"1494301487049":{"type":"menu","settings":{"show_footer_title":true,"menu":"our-shop","container_width":25}},"15ab9ab0-d46d-40e6-a751-e70575182e63":{"type":"menu","settings":{"show_footer_title":true,"menu":"my-account","container_width":25}}},"block_order":["9e680033-3ce9-4c32-8ec1-a994ad408f27","f79f7187-a92b-4f1f-9d47-6305d2baca5f","1494301487049","15ab9ab0-d46d-40e6-a751-e70575182e63"],"settings":{"show_locale_selector":true,"show_currency_selector":true,"show_currency_flags":true,"show_payment_icons":true,"show_copyright":true,"copyright_text":""}}},"order":["footer-promotions","footer"]}